setup.cfg
setup.py
ftio/__init__.py
ftio.egg-info/PKG-INFO
ftio.egg-info/SOURCES.txt
ftio.egg-info/dependency_links.txt
ftio.egg-info/top_level.txt
ftio/wiki/__init__.py
ftio/wiki/preproc.py